ccl_leveldbases.py
ccl_leveldbases-1.2.3.dist-info/LICENSE
ccl_leveldbases-1.2.3.dist-info/METADATA
ccl_leveldbases-1.2.3.dist-info/WHEEL
ccl_leveldbases-1.2.3.dist-info/RECORD
