Metadata-Version: 2.1
Name: ccl_leveldbases
Version: 1.2.3
Summary: CCL Leveldb Reader, extract vault data from any chrome extensions, and etc.
License: MIT
Author: JeanClaude89
Requires-Python: >=3.7,<4.0
Classifier: License :: OSI Approved :: MIT License
Classifier: Programming Language :: Python :: 3
Classifier: Programming Language :: Python :: 3.7
Classifier: Programming Language :: Python :: 3.8
Classifier: Programming Language :: Python :: 3.9
Classifier: Programming Language :: Python :: 3.10
Classifier: Programming Language :: Python :: 3.11
Classifier: Programming Language :: Python :: 3.12
